{
  "info": {
    "description": "data",
    "version": "1.0",
    "year": 2025,
    "contributor": "search engine",
    "source": "no_augmentation",
    "license": {
      "name": "Creative Commons Attribution 4.0 International",
      "url": "https://creativecommons.org/licenses/by/4.0/"
    },
    "leaf_info": {}
  },
  "images": [
    {
      "id": 9597768428,
      "width": 256,
      "height": 256,
      "file_name": "image (810).JPG",
      "size": 13958,
      "format": "JPG",
      "url": "",
      "hash": "",
      "status": "success",
      "pvc_filename": "RS_Rust 2382.JPG"
    }
  ],
  "annotations": [
    {
      "id": 8868424435,
      "image_id": 9597768428,
      "category_id": 2000000008,
      "segmentation": [],
      "area": 3702,
      "bbox": [
        0,
        185,
        98,
        71
      ]
    },
    {
      "id": 9754430435,
      "image_id": 9597768428,
      "category_id": 2000000008,
      "segmentation": [],
      "area": 6257,
      "bbox": [
        171,
        0,
        85,
        256
      ]
    },
    {
      "id": 4856557435,
      "image_id": 9597768428,
      "category_id": 2000000008,
      "segmentation": [],
      "area": 250,
      "bbox": [
        144,
        156,
        21,
        23
      ]
    },
    {
      "id": 1707223435,
      "image_id": 9597768428,
      "category_id": 2000000008,
      "segmentation": [],
      "area": 2405,
      "bbox": [
        48,
        30,
        50,
        136
      ]
    },
    {
      "id": 9672872435,
      "image_id": 9597768428,
      "category_id": 2000000008,
      "segmentation": [],
      "area": 135,
      "bbox": [
        22,
        114,
        10,
        35
      ]
    },
    {
      "id": 3992555435,
      "image_id": 9597768428,
      "category_id": 2000000008,
      "segmentation": [],
      "area": 206,
      "bbox": [
        136,
        110,
        22,
        23
      ]
    },
    {
      "id": 2546329435,
      "image_id": 9597768428,
      "category_id": 2000000008,
      "segmentation": [],
      "area": 127,
      "bbox": [
        152,
        96,
        15,
        14
      ]
    },
    {
      "id": 8357925435,
      "image_id": 9597768428,
      "category_id": 2000000008,
      "segmentation": [],
      "area": 3027,
      "bbox": [
        0,
        0,
        103,
        70
      ]
    }
  ],
  "categories": [
    {
      "id": 2000000008,
      "name": "Common_rust",
      "supercategory": "Corn"
    }
  ]
}