{
  "info": {
    "description": "data",
    "version": "1.0",
    "year": 2025,
    "contributor": "search engine",
    "source": "no_augmentation",
    "license": {
      "name": "Creative Commons Attribution 4.0 International",
      "url": "https://creativecommons.org/licenses/by/4.0/"
    },
    "leaf_info": {}
  },
  "images": [
    {
      "id": 7672415227,
      "width": 256,
      "height": 256,
      "file_name": "image (695).JPG",
      "size": 16833,
      "format": "JPG",
      "url": "",
      "hash": "",
      "status": "success",
      "original_filename": "RS_NLB 3724.JPG",
      "pvc_filename": "b289a3cb-17e1-4889-8b12-bbee01d7b4e8___RS_NLB 3724.JPG"
    }
  ],
  "annotations": [
    {
      "id": 8400396233,
      "image_id": 7672415227,
      "category_id": 2000000010,
      "segmentation": [],
      "area": 384,
      "bbox": [
        26,
        165,
        14,
        91
      ]
    },
    {
      "id": 9102907233,
      "image_id": 7672415227,
      "category_id": 2000000010,
      "segmentation": [],
      "area": 264,
      "bbox": [
        201,
        198,
        14,
        42
      ]
    },
    {
      "id": 1901308233,
      "image_id": 7672415227,
      "category_id": 2000000010,
      "segmentation": [],
      "area": 6087,
      "bbox": [
        43,
        26,
        69,
        182
      ]
    },
    {
      "id": 3359510233,
      "image_id": 7672415227,
      "category_id": 2000000010,
      "segmentation": [],
      "area": 149,
      "bbox": [
        130,
        180,
        9,
        25
      ]
    },
    {
      "id": 8365867233,
      "image_id": 7672415227,
      "category_id": 2000000010,
      "segmentation": [],
      "area": 128,
      "bbox": [
        219,
        165,
        11,
        21
      ]
    },
    {
      "id": 8093949233,
      "image_id": 7672415227,
      "category_id": 2000000010,
      "segmentation": [],
      "area": 145,
      "bbox": [
        183,
        167,
        17,
        15
      ]
    },
    {
      "id": 5542061233,
      "image_id": 7672415227,
      "category_id": 2000000010,
      "segmentation": [],
      "area": 236,
      "bbox": [
        193,
        112,
        16,
        66
      ]
    },
    {
      "id": 3664151233,
      "image_id": 7672415227,
      "category_id": 2000000010,
      "segmentation": [],
      "area": 4002,
      "bbox": [
        180,
        0,
        48,
        171
      ]
    },
    {
      "id": 5149935233,
      "image_id": 7672415227,
      "category_id": 2000000010,
      "segmentation": [],
      "area": 679,
      "bbox": [
        160,
        87,
        16,
        83
      ]
    },
    {
      "id": 2050704233,
      "image_id": 7672415227,
      "category_id": 2000000010,
      "segmentation": [],
      "area": 847,
      "bbox": [
        28,
        0,
        44,
        148
      ]
    },
    {
      "id": 6361905233,
      "image_id": 7672415227,
      "category_id": 2000000010,
      "segmentation": [],
      "area": 115,
      "bbox": [
        243,
        112,
        13,
        13
      ]
    },
    {
      "id": 8998740233,
      "image_id": 7672415227,
      "category_id": 2000000010,
      "segmentation": [],
      "area": 344,
      "bbox": [
        240,
        32,
        16,
        47
      ]
    },
    {
      "id": 3304786233,
      "image_id": 7672415227,
      "category_id": 2000000010,
      "segmentation": [],
      "area": 172,
      "bbox": [
        222,
        48,
        21,
        15
      ]
    }
  ],
  "categories": [
    {
      "id": 2000000010,
      "name": "Northern_Leaf_Blight",
      "supercategory": "Corn"
    }
  ]
}