{
  "info": {
    "description": "data",
    "version": "1.0",
    "year": 2025,
    "contributor": "search engine",
    "source": "no_augmentation",
    "license": {
      "name": "Creative Commons Attribution 4.0 International",
      "url": "https://creativecommons.org/licenses/by/4.0/"
    },
    "leaf_info": {}
  },
  "images": [
    {
      "id": 7387032571,
      "width": 256,
      "height": 256,
      "file_name": "image (480).JPG",
      "size": 7549,
      "format": "JPG",
      "url": "",
      "hash": "",
      "status": "success",
      "original_filename": "RS_NLB 3916.JPG",
      "pvc_filename": "3428ab03-a782-43d1-8d21-8f3405666867___RS_NLB 3916.JPG"
    }
  ],
  "annotations": [
    {
      "id": 8542083581,
      "image_id": 7387032571,
      "category_id": 2000000010,
      "segmentation": [],
      "area": 15141,
      "bbox": [
        73,
        0,
        142,
        200
      ]
    }
  ],
  "categories": [
    {
      "id": 2000000010,
      "name": "Northern_Leaf_Blight",
      "supercategory": "Corn"
    }
  ]
}