{
  "info": {
    "description": "data",
    "version": "1.0",
    "year": 2025,
    "contributor": "search engine",
    "source": "no_augmentation",
    "license": {
      "name": "Creative Commons Attribution 4.0 International",
      "url": "https://creativecommons.org/licenses/by/4.0/"
    },
    "leaf_info": {
      "leaf_number": 1.0,
      "source": "plant_village_classification",
      "original_filename": "RS_Rust 1963_final_masked_1.jpg"
    }
  },
  "images": [
    {
      "id": 1672922689,
      "width": 256,
      "height": 256,
      "file_name": "cb6f530e-f626-4ced-846f-f88528f10da4___RS_Rust 1963_final_masked_1.jpg",
      "size": 11310,
      "format": "JPG",
      "url": "",
      "hash": "",
      "status": "success",
      "original_filename": "RS_Rust 1963_final_masked_1.jpg",
      "pvc_filename": "cb6f530e-f626-4ced-846f-f88528f10da4___RS_Rust 1963_final_masked_1.jpg"
    }
  ],
  "annotations": [],
  "categories": [
    {
      "id": 2000000003,
      "name": "common_rust",
      "supercategory": "Corn"
    }
  ]
}