{
  "info": {
    "description": "data",
    "version": "1.0",
    "year": 2025,
    "contributor": "search engine",
    "source": "augmented",
    "license": {
      "name": "Creative Commons Attribution 4.0 International",
      "url": "https://creativecommons.org/licenses/by/4.0/"
    }
  },
  "images": [
    {
      "id": 4092105959,
      "width": 256,
      "height": 256,
      "file_name": "image (372).JPG",
      "size": 14114,
      "format": "JPG",
      "url": "",
      "hash": "",
      "status": "success"
    }
  ],
  "annotations": [
    {
      "id": 7837582968,
      "image_id": 4092105959,
      "category_id": 1000000010,
      "segmentation": [],
      "area": 26606,
      "bbox": [
        14,
        0,
        193,
        256
      ]
    },
    {
      "id": 3869342968,
      "image_id": 4092105959,
      "category_id": 1000000010,
      "segmentation": [],
      "area": 111,
      "bbox": [
        59,
        159,
        12,
        18
      ]
    },
    {
      "id": 5417691968,
      "image_id": 4092105959,
      "category_id": 1000000010,
      "segmentation": [],
      "area": 250,
      "bbox": [
        64,
        62,
        19,
        35
      ]
    }
  ],
  "categories": [
    {
      "id": 1000000010,
      "name": "Northern_Leaf_Blight",
      "supercategory": "Corn"
    }
  ]
}